<?xml version="1.0" encoding="UTF-8" standalone="no"?>
<TcBusinessDataLocalization xmlns="http://teamcenter.com/BusinessModel/TcBusinessDataLocalization" Date="Fri Jul 02 08:38:12 AM 2021">
    <Add>
   <key id="BusinessObject{::}ETSTranslationRequest" locale="it_IT" status="Approved">Richiesta di conversione</key>
   <key id="Property{::}ETSTranslationRequest{::}primary_objs" locale="it_IT" status="Approved">Oggetti primari</key>
   <key id="Property{::}ETSTranslationRequest{::}provider_name" locale="it_IT" status="Approved">Nome fornitore</key>
   <key id="Property{::}ETSTranslationRequest{::}sched_priority" locale="it_IT" status="Approved">Priorità</key>
   <key id="Property{::}ETSTranslationRequest{::}secondary_objs" locale="it_IT" status="Approved">Oggetti secondari</key>
   <key id="Property{::}ETSTranslationRequest{::}state_dates" locale="it_IT" status="Approved">Date degli stati</key>
   <key id="Property{::}ETSTranslationRequest{::}states" locale="it_IT" status="Approved">Stati</key>
   <key id="Property{::}ETSTranslationRequest{::}state" locale="it_IT" status="Approved">Stato</key>
   <key id="Property{::}ETSTranslationRequest{::}task_id" locale="it_IT" status="Approved">ID attività</key>
   <key id="Property{::}ETSTranslationRequest{::}translation_args" locale="it_IT" status="Approved">Argomenti conversione</key>
   <key id="Property{::}ETSTranslationRequest{::}translator_name" locale="it_IT" status="Approved">Nome convertitore</key>
</Add>
</TcBusinessDataLocalization>
